{
  "name": "2nd floor",
  "mapFileName": "middlesex-f1.png",
  "showLegend": true,
  "legendPosition": [
    0,
    0,
    1,
    1
  ],
  "layers": [
    {
      "name": "Main Map",
      "color": "BLACK",
      "layerType": "base",
      "font": "Times New Roman",
      "size": 16,
      "points": [
        {
          "x": 100,
          "y": 100,
          "name": "Floor2-a",
          "roomNumber": "A100",
          "description": "Class room A100",
          "type": "ClassRoom"
        },
        {
          "x": 200,
          "y": 200,
          "name": "Floor2-b",
          "roomNumber": "A200",
          "description": "Class room A200",
          "type": "ClassRoom"
        }
      ]
    },
    {
      "name": "Main Map",
      "color": "BLACK",
      "layerType": "internal",
      "font": "Times New Roman",
      "size": 16,
      "points": [
        {
          "x": 300,
          "y": 400,
          "name": "Floor2-My Test1",
          "roomNumber": "A100",
          "description": "Class room A100",
          "type": "ClassRoom"
        },
        {
          "x": 500,
          "y": 700,
          "name": "Floor2-My Test2",
          "roomNumber": "A200",
          "description": "Class room A200",
          "type": "ClassRoom"
        }
      ]
    }
  ]
}
